LICENCE
README.md
setup.py
linescounter/__init__.py
linescounter/__main__.py
linescounter/linescounter.py
linescounter.egg-info/PKG-INFO
linescounter.egg-info/SOURCES.txt
linescounter.egg-info/dependency_links.txt
linescounter.egg-info/entry_points.txt
linescounter.egg-info/requires.txt
linescounter.egg-info/top_level.txt
linescounter/functions/__init__.py
linescounter/options/__init__.py
linescounter/options/full.py
linescounter/options/ignore.py
linescounter/options/only.py
tests/__init__.py
tests/test_countlines.py