Metadata-Version: 2.1
Name: linescounter
Version: 1.0.0
Summary: LinesCounter - Command line tool that counts your project's lines, and other cool features
Home-page: https://github.com/nawafalqari/linescounter/
Author: Nawaf and Khayal
Author-email: nawafalqari13@gmail.com
License: MIT
Keywords: linescounter,lines,words,lines counter,count
Platform: UNKNOWN
Classifier: License :: OSI Approved :: MIT License
Classifier: Programming Language :: Python :: 2.7
Classifier: Programming Language :: Python :: 3
Classifier: Programming Language :: Python :: 3.7
License-File: LICENCE
